cm/__init__.py
cm/functions.py
cm/launcher.py
cm/main_operator.py
cm/video_worker.py
cm/wlistener.py
cm/configs/__init__.py
cm/configs/config.py
cm/configs/settings.py
cm/gcore_interaction/__init__.py
cm/gcore_interaction/db_functions.py
cm/gcore_interaction/db_functions_higher.py
cm/gcore_interaction/tests/__init__.py
cm/gcore_interaction/tests/test_db_function.py
cm/imgs/__init__.py
cm/imgs/abort.png
cm/imgs/abortFiltres.png
cm/imgs/abortFiltresZ.png
cm/imgs/abortRound.png
cm/imgs/abortRoundUnactive.png
cm/imgs/abortRoundZ.png
cm/imgs/abortZ.png
cm/imgs/accept.png
cm/imgs/acceptZ.png
cm/imgs/addComm.png
cm/imgs/ar_connection_lost_win.png
cm/imgs/auto_gate_control.png
cm/imgs/auto_gate_controlZ.png
cm/imgs/backscreen — копия.png
cm/imgs/backscreen.png
cm/imgs/brutto_too_little_win.png
cm/imgs/calendarwin.png
cm/imgs/camera_is_connecting.png
cm/imgs/camera_is_not_available.png
cm/imgs/cancel.png
cm/imgs/cancelZ.png
cm/imgs/cancel_tare.png
cm/imgs/car_in.png
cm/imgs/car_out.png
cm/imgs/car_pass_btn.png
cm/imgs/car_pass_btnZ.png
cm/imgs/car_passs_btn.png
cm/imgs/car_passs_btnZ.png
cm/imgs/change.png
cm/imgs/changeZ.png
cm/imgs/chatDecline.png
cm/imgs/chatbg.png
cm/imgs/chatcommit.png
cm/imgs/chatexit.png
cm/imgs/chaticon.png
cm/imgs/close.png
cm/imgs/closeZ.png
cm/imgs/close_recs.png
cm/imgs/continue_waiting_btn.png
cm/imgs/continue_waiting_btnZ.png
cm/imgs/currentEvents.png
cm/imgs/decline.png
cm/imgs/declineZ.png
cm/imgs/disputswin.png
cm/imgs/ensureCloseRec.png
cm/imgs/enter.png
cm/imgs/enterZ.png
cm/imgs/exit.png
cm/imgs/exitZ.png
cm/imgs/exitwin.png
cm/imgs/export_1c_btn.png
cm/imgs/export_1c_btnZ.png
cm/imgs/export_excel.png
cm/imgs/export_excelZ.png
cm/imgs/fakeTree.png
cm/imgs/forbwin.png
cm/imgs/frontscreen.png
cm/imgs/gateL.png
cm/imgs/gateR.png
cm/imgs/gate_arrow.png
cm/imgs/gate_base.png
cm/imgs/kpp_abort_btn.png
cm/imgs/kpp_abort_btnZ.png
cm/imgs/kpp_abort_photocell_car_pass_btn.png
cm/imgs/kpp_abort_photocell_car_pass_btnZ.png
cm_two-3.1.32.dist-info/licenses/LICENSE
cm_two-3.1.32.dist-info/METADATA
cm_two-3.1.32.dist-info/WHEEL
cm_two-3.1.32.dist-info/top_level.txt
cm_two-3.1.32.dist-info/RECORD
