Metadata-Version: 2.4
Name: cm_two
Version: 3.1.32
Author: PunchyArchy
License-File: LICENSE
Requires-Dist: tk
Requires-Dist: pillow
Requires-Dist: pyautogui
Requires-Dist: tkcalendar
Requires-Dist: screeninfo
Requires-Dist: psycopg-binary
Requires-Dist: gtki_module_exex
Requires-Dist: gtki_module_treeview==2.9
Requires-Dist: qodex_pi==0.9.1
Requires-Dist: qsct==0.95
Requires-Dist: cmadb==0.0.1
Requires-Dist: cm_qdk==0.0.1
Requires-Dist: imutils
Requires-Dist: numpy
Requires-Dist: opencv-python>=4.8
Requires-Dist: fontTools
Requires-Dist: setuptools
Requires-Dist: wsqluse
Requires-Dist: XLsxWriter==3.0.3
Requires-Dist: ar_one_qdk
Requires-Dist: Cython
Dynamic: author
Dynamic: license-file
Dynamic: requires-dist
